arcane/ga4/__init__.py
arcane/ga4/client.py
arcane/ga4/exception.py
arcane/ga4/helpers.py
arcane_ga4-0.4.5.dist-info/METADATA
arcane_ga4-0.4.5.dist-info/WHEEL
arcane_ga4-0.4.5.dist-info/RECORD
